spriteutil_detection/__init__.py
spriteutil_detection/spriteutil.py
spriteutil_detection-1.0.2.dist-info/LICENSE
spriteutil_detection-1.0.2.dist-info/METADATA
spriteutil_detection-1.0.2.dist-info/WHEEL
spriteutil_detection-1.0.2.dist-info/top_level.txt
spriteutil_detection-1.0.2.dist-info/RECORD
