Metadata-Version: 2.1
Name: spriteutil-detection
Version: 1.0.2
Summary: A small example package
Home-page: https://github.com/intek-training-jsc/sprite-sheet-duyphungbatch3
Author: Phuong Duy PHUNG
Author-email: duy.phung@f4.intek.edu.vn
License: UNKNOWN
Platform: UNKNOWN
Classifier: Programming Language :: Python :: 3
Classifier: License :: OSI Approved :: MIT License
Classifier: Operating System :: OS Independent
Requires-Python: >=3.6
Requires-Dist: bleach (==3.1.0)
Requires-Dist: certifi (==2019.11.28)
Requires-Dist: cffi (==1.13.2)
Requires-Dist: chardet (==3.0.4)
Requires-Dist: cryptography (==2.8)
Requires-Dist: docutils (==0.16)
Requires-Dist: idna (==2.8)
Requires-Dist: keyring (==21.1.0)
Requires-Dist: more-itertools (==8.1.0)
Requires-Dist: numpy (==1.18.1)
Requires-Dist: pillow (==7.0.0)
Requires-Dist: pipfile (==0.0.2)
Requires-Dist: pkginfo (==1.5.0.1)
Requires-Dist: pycparser (==2.19)
Requires-Dist: pygments (==2.5.2)
Requires-Dist: readme-renderer (==24.0)
Requires-Dist: requests (==2.22.0)
Requires-Dist: requests-toolbelt (==0.9.1)
Requires-Dist: six (==1.14.0)
Requires-Dist: toml (==0.10.0)
Requires-Dist: tqdm (==4.41.1)
Requires-Dist: twine (==3.1.1)
Requires-Dist: urllib3 (==1.25.7)
Requires-Dist: webencodings (==0.5.1)
Requires-Dist: wheel (==0.33.6)
Requires-Dist: zipp (==1.0.0)
Requires-Dist: importlib-metadata (==1.4.0) ; python_version < "3.8"
Requires-Dist: jeepney (==0.4.2) ; sys_platform == "linux"
Requires-Dist: secretstorage (==3.1.2) ; sys_platform == "linux"
Provides-Extra: dev
Requires-Dist: appdirs (==1.4.3) ; extra == 'dev'
Requires-Dist: astroid (==2.3.3) ; extra == 'dev'
Requires-Dist: attrs (==19.3.0) ; extra == 'dev'
Requires-Dist: cached-property (==1.5.1) ; extra == 'dev'
Requires-Dist: cerberus (==1.3.2) ; extra == 'dev'
Requires-Dist: certifi (==2019.11.28) ; extra == 'dev'
Requires-Dist: chardet (==3.0.4) ; extra == 'dev'
Requires-Dist: click (==7.0) ; extra == 'dev'
Requires-Dist: colorama (==0.4.1) ; extra == 'dev'
Requires-Dist: distlib (==0.3.0) ; extra == 'dev'
Requires-Dist: first (==2.0.2) ; extra == 'dev'
Requires-Dist: idna (==2.8) ; extra == 'dev'
Requires-Dist: isort (==4.3.21) ; extra == 'dev'
Requires-Dist: lazy-object-proxy (==1.4.3) ; extra == 'dev'
Requires-Dist: mccabe (==0.6.1) ; extra == 'dev'
Requires-Dist: more-itertools (==8.1.0) ; extra == 'dev'
Requires-Dist: orderedmultidict (==1.0.1) ; extra == 'dev'
Requires-Dist: packaging (==19.2) ; extra == 'dev'
Requires-Dist: pathspec (==0.7.0) ; extra == 'dev'
Requires-Dist: pep517 (==0.8.1) ; extra == 'dev'
Requires-Dist: pip-shims (==0.4.0) ; extra == 'dev'
Requires-Dist: pipenv-setup (==2.2.5) ; extra == 'dev'
Requires-Dist: pipfile (==0.0.2) ; extra == 'dev'
Requires-Dist: plette[validation] (==0.2.3) ; extra == 'dev'
Requires-Dist: pylint (==2.4.4) ; extra == 'dev'
Requires-Dist: pyparsing (==2.4.6) ; extra == 'dev'
Requires-Dist: regex (==2020.1.8) ; extra == 'dev'
Requires-Dist: requests (==2.22.0) ; extra == 'dev'
Requires-Dist: requirementslib (==1.5.3) ; extra == 'dev'
Requires-Dist: six (==1.14.0) ; extra == 'dev'
Requires-Dist: toml (==0.10.0) ; extra == 'dev'
Requires-Dist: tomlkit (==0.5.8) ; extra == 'dev'
Requires-Dist: typing (==3.7.4.1) ; extra == 'dev'
Requires-Dist: urllib3 (==1.25.7) ; extra == 'dev'
Requires-Dist: vistir (==0.5.0) ; extra == 'dev'
Requires-Dist: wheel (==0.33.6) ; extra == 'dev'
Requires-Dist: wrapt (==1.11.2) ; extra == 'dev'
Requires-Dist: zipp (==1.0.0) ; extra == 'dev'
Requires-Dist: typed-ast (==1.4.1) ; (implementation_name == "cpython" and python_version < "3.8") and extra == 'dev'
Requires-Dist: importlib-metadata (==1.4.0) ; (python_version < "3.8") and extra == 'dev'
Requires-Dist: black (==19.10b0) ; (python_version >= "3.6") and extra == 'dev'
